Metadata-Version: 2.1
Name: d8s-hashes
Version: 0.6.0
Summary: Democritus functions for working with hashes.
Home-page: https://github.com/democritus-project/d8s-hashes
Author: Floyd Hightower
Author-email: floyd.hightower27@gmail.com
License: GNU Lesser General Public License v3
Keywords: democritus,utility,python,hashes,hashes-utility,md5,sha1,sha256,sha512,ssdeep_compare,ssdeep
Platform: UNKNOWN
Classifier: Development Status :: 2 - Pre-Alpha
Classifier: Intended Audience :: Developers
Classifier: License :: OSI Approved :: GNU Lesser General Public License v3 or later (LGPLv3+)
Classifier: Natural Language :: English
Classifier: Programming Language :: Python :: 3
Classifier: Programming Language :: Python :: 3.4
Classifier: Programming Language :: Python :: 3.5
Classifier: Programming Language :: Python :: 3.6
Classifier: Programming Language :: Python :: 3.7
Classifier: Programming Language :: Python :: 3.8
Classifier: Programming Language :: Python :: 3.9
Requires-Dist: ppdeep
Requires-Dist: importlib-metadata ; python_version < "3.8"
